falcon_rpc/__init__.py
falcon_rpc/errors.py
falcon_rpc/logger_ext.py
falcon_rpc/rpc.py
falcon_rpc-0.5.0.dist-info/LICENSE
falcon_rpc-0.5.0.dist-info/METADATA
falcon_rpc-0.5.0.dist-info/WHEEL
falcon_rpc-0.5.0.dist-info/top_level.txt
falcon_rpc-0.5.0.dist-info/RECORD
