Metadata-Version: 2.1
Name: falcon-rpc
Version: 0.5.0
Summary: RPC API based on the Falcon Framework
Home-page: UNKNOWN
License: UNKNOWN
Platform: UNKNOWN
Requires-Dist: falcon (==2.0.0)
Requires-Dist: falcon-cors
